{"akt": ["ak", "125-sl", "125", "ak", "adventure", "dynamic", "jet-4", "ak", "110", "110-x", "125-sport", "ak", "evo", "flex-ultra", "tvs", "rtx", "tt"], "bajaj": ["motocarro", "discover", "platino", "boxer", "pulsar"], "honda": ["cb", "shadow", "xl", "xr", "xre", "super-sport", "cbr", "turismo", "elite", "space-an", "click", "dio", "navi", "wave", "c-100", "cb", "sport", "cbf", "e-storm", "tornado", "biz", "eco", "hero"], "kawasaki": ["vulcan", "klx", "er-6n", "z", "versys", "ninja"], "ktm": ["enduro", "adventure-s", "lc", "duke"], "kymco": ["agility", "fly", "rocket", "twist", "urban", "spike", "top-boy"], "piaggio": ["motocarro", "ape-501", "scooter"], "sachs": ["madass"], "suzuki": ["gz", "dr", "gsr", "gsx", "super-sport", "gs", "dr", "dl1000", "dl650", "gladius", "sport", "inazuma", "best", "lets", "burgman", "gs", "ax", "gn", "gz", "ts", "xf", "viva-r", "hayate", "lets", "best", "gixxer", "dr", "dl", "gsx"], "tvs": ["apache", "sport"], "um": ["renegade", "dsr-ii", "powermax", "commett", "xtreet-ii"], "yamaha": ["xl", "pw", "xtz", "virago", "xt", "yz", "dt", "xt", "xtz", "r600", "fz", "yzf", "fazer", "mt07", "mt", "bws", "crypton", "fino", "yw-100", "nmax", "libero", "t115", "sz-r", "rx", "ybr"]}